<properties id="1">
  <property name="PushedUnitScrappedChance" value="20"/>
  <property name="ForceProduceAndCaptureProtos" value="false"/>
  <property name="DefenderWinModifierExperienceFlat" value="20"/>
  <property name="RealBlindDrop" value="true"/>
  <property name="BVRatioPercent" value="105"/>
  <property name="TimeToNondefensePenalty" value="180"/>
  <property name="MinDefenderNonInfantry" value="2"/>
  <property name="AttackerAllowedAeros" value="true"/>
  <property name="AttackerAllowedMeks" value="false"/>
  <property name="MapMedium" value="2"/>
  <property name="BaseAttackerPayCBills" value="480"/>
  <property name="RPForDefender" value="1"/>
  <property name="PercentInfluenceChickenPenalty" value="1"/>
  <property name="DefenderAllowedVehs" value="false"/>
  <property name="BaseDefenderPayInfluence" value="20"/>
  <property name="MinAttackerBV" value="2000"/>
  <property name="DeploySoutheastdeep" value="1"/>
  <property name="PercentageToAttackOnWorld" value="33"/>
  <property name="MaxAttackerBV" value="5000"/>
  <property name="UseBVRatioPercent" value="true"/>
  <property name="BaseDefenderPayCBills" value="576"/>
  <property name="MinAttackerAero" value="2"/>
  <property name="DefenderPayBVforCBill" value="2.500"/>
  <property name="PercentageToAttackOffWorld" value="66"/>
  <property name="AttackerPayBVforCBill" value="3.000"/>
  <property name="DefenderAllowedInf" value="false"/>
  <property name="MinDefenderMeks" value="0"/>
  <property name="AttackerLossModifierCBillsPercent" value="33"/>
  <property name="DeployEast" value="0"/>
  <property name="NumberOfVictoryConditions" value="2"/>
  <property name="MaxDefenderAero" value="10"/>
  <property name="RandomDeployment" value="true"/>
  <property name="MaxPlanetOwnership" value="500"/>
  <property name="MinBVDifferenceForFullPay" value="0.20"/>
  <property name="FailurePenalty" value="2000"/>
  <property name="DefenderAllowedMeks" value="false"/>
  <property name="DeploySoutheast" value="0"/>
  <property name="PercentRPChickenPenalty" value=".10"/>
  <property name="DeploySouth" value="0"/>
  <property name="MapSizeY" value="45"/>
  <property name="RPForAttacker" value="2"/>
  <property name="MapSizeX" value="45"/>
  <property name="MinDefenderBV" value="2000"/>
  <property name="DeployNorth" value="0"/>
  <property name="Valkyrie" value="Probe"/>
  <property name="DestroyEnemyBV" value="50"/>
  <property name="LegalAttackFactions" value="Comstar"/>
  <property name="MaxDefenderBV" value="6000"/>
  <property name="DefenderLossModifierCBillsPercent" value="33"/>
  <property name="AttackerCostInfluence" value="30"/>
  <property name="PushedUnitSalvageChance" value="40"/>
  <property name="DebugOp" value="true"/>
  <property name="OnlyGiveRPtoWinners" value="true"/>
  <property name="DeployNorthwestdeep" value="1"/>
  <property name="DeploySouthdeep" value="1"/>
  <property name="DefenderPayBVforInfluence" value="100"/>
  <property name="ForceProduceAndCaptureInfs" value="false"/>
  <property name="DisallowPlanetFlags" value="1"/>
  <property name="DeployNortheast" value="0"/>
  <property name="DeployWest" value="0"/>
  <property name="MinAttackerMeks" value="0"/>
  <property name="DeployWestdeep" value="1"/>
  <property name="UseDestroyEnemyBV" value="true"/>
  <property name="BaseDefenderPayExperience" value="30"/>
  <property name="MinAttackerNonInfantry" value="2"/>
  <property name="BaseAttackerPayExperience" value="30"/>
  <property name="DefenderAllowedAeros" value="true"/>
  <property name="BVFailurePaymentModifier" value="25"/>
  <property name="MaxAttackerAero" value="10"/>
  <property name="DefenderLossModifierInfluencePercent" value="33"/>
  <property name="DeployNorthdeep" value="1"/>
  <property name="AttackerWinModifierExperienceFlat" value="20"/>
  <property name="DeploySouthwest" value="0"/>
  <property name="ForceProduceAndCaptureBAs" value="false"/>
  <property name="IllegalDefendFactions" value="Comstar$Solaris Training Company"/>
  <property name="AttackerAllowedVehs" value="false"/>
  <property name="ForbidCounterAttacks" value="true"/>
  <property name="OperationColor" value="#5F3F00"/>
  <property name="MinDefenderAero" value="2"/>
  <property name="PercentCBillChickenPenalty" value=".10"/>
  <property name="CountGameForRanking" value="false"/>
  <property name="DeploySouthwestdeep" value="1"/>
  <property name="OperationRange" value="1000"/>
  <property name="DeployEastdeep" value="1"/>
  <property name="OnlyAgainstNonHomeWorlds" value="false"/>
  <property name="DeployNorthwest" value="0"/>
  <property name="OnlyAllowedFromActive" value="true"/>
  <property name="DeployNortheastdeep" value="1"/>
  <property name="AttackerAllowedInf" value="false"/>
</properties>